Comparator/Comparator.v
module comparator(A,B,AgBr);
	input [1:0] A,B;
	output AgBr;
	reg AgB;
	assign AgBr = AgB;
	always@(A or B)
		begin
			if (A>B)
				AgB=1'b1;
			else AgB=1'b0;
		end
endmodule

Comparator/test_com.v
module test;
	reg [1:0] A, B;
	wire AgB;
	comparator a(.A(A), .B(B), .AgBr(AgB));
	initial 
		begin
			A=2'b00; B=2'b11;
			#24 A=2'b01; B=2'b11;
			#12 A=2'b10; B=2'b11;
			#15 A=2'b11; B=2'b11;
			
			#15 A=2'b00; B=2'b10;
			#24 A=2'b01; B=2'b10;
			#12 A=2'b10; B=2'b10;
			#15 A=2'b11; B=2'b10;
			
			#17 A=2'b00; B=2'b01;
			#24 A=2'b01; B=2'b01;
			#12 A=2'b10; B=2'b01;
			#15 A=2'b11; B=2'b01;
			
			#23 A=2'b00; B=2'b00;
			#24 A=2'b01; B=2'b00;
			#12 A=2'b10; B=2'b00;
			#15 A=2'b11; B=2'b00;
		end
	
	initial 
		begin
		$dumpfile("test.vcd");
			$dumpvars(0,test);
		end
endmodule

Comparator/Outputs/test.vcd
$date
	Fri Sep 30 23:19:01 2022
$end
$version
	Icarus Verilog
$end
$timescale
	1s
$end
$scope module test $end
$var wire 1 ! AgB $end
$var reg 2 " A [1:0] $end
$var reg 2 # B [1:0] $end
$scope module a $end
$var wire 2 $ A [1:0] $end
$var wire 1 ! AgBr $end
$var wire 2 % B [1:0] $end
$var reg 1 & AgB $end
$upscope $end
$upscope $end
$enddefinitions $end
#0
$dumpvars
0&
b11 %
b0 $
b11 #
b0 "
0!
$end
#24
b1 "
b1 $
#36
b10 "
b10 $
#51
b11 "
b11 $
#66
b10 #
b10 %
b0 "
b0 $
#90
b1 "
b1 $
#102
b10 "
b10 $
#117
1!
1&
b11 "
b11 $
#134
0!
0&
b1 #
b1 %
b0 "
b0 $
#158
b1 "
b1 $
#170
1!
1&
b10 "
b10 $
#185
b11 "
b11 $
#208
0!
0&
b0 #
b0 %
b0 "
b0 $
#232
1!
1&
b1 "
b1 $
#244
b10 "
b10 $
#259
b11 "
b11 $
