Barrel_Shifter/Barrel_shifter.v
module barrel_shifter(Data, dir, bits_shift, bits_data);
	input [7:0] Data;
	input dir;
	input [2:0] bits_shift;
	output reg [7:0] bits_data;
	always@*
		begin
			case({dir, bits_shift})	
				4'b0001: bits_data = {Data[0],Data[7:1]};
				4'b0010: bits_data = {Data[1:0],Data[7:2]};
				4'b0011: bits_data = {Data[2:0],Data[7:3]};
				4'b0100: bits_data = {Data[3:0],Data[7:4]};
				4'b0101: bits_data = {Data[4:0],Data[7:5]};
				4'b0110: bits_data = {Data[5:0],Data[7:6]};
				4'b0111: bits_data = {Data[6:0],Data[7]};
				4'b1001: bits_data = {Data[6:0],Data[7]};
				4'b1010: bits_data = {Data[5:0],Data[7:6]};
				4'b1011: bits_data = {Data[4:0],Data[7:5]};
				4'b1100: bits_data = {Data[3:0],Data[7:4]};
				4'b1101: bits_data = {Data[2:0],Data[7:3]};
				4'b1110: bits_data = {Data[1:0],Data[7:2]};
				4'b1111: bits_data = {Data[0],Data[7:1]};
				default: bits_data = Data;
			endcase
		end
endmodule

Barrel_Shifter/test.v
module test;
	wire [7:0] Data;
	reg dir;
	reg [2:0] bits_shift;
	wire [7:0] bits_data;
	barrel_shifter bs(Data, dir, bits_shift, bits_data);
	assign Data = 8'b10001110;
	
	
	initial
		begin
			dir = 1; bits_shift = 3'b000;
			#12 dir = 1; bits_shift = 3'b001;
			#12 dir = 1; bits_shift = 3'b010;
			#12 dir = 1; bits_shift = 3'b011;
			#12 dir = 1; bits_shift = 3'b100;
			#12 dir = 1; bits_shift = 3'b101;
			#12 dir = 1; bits_shift = 3'b110;
			#12 dir = 1; bits_shift = 3'b111;
			
			#12 dir = 0; bits_shift = 3'b000;
			#12 dir = 0; bits_shift = 3'b001;
			#12 dir = 0; bits_shift = 3'b010;
			#12 dir = 0; bits_shift = 3'b011;
			#12 dir = 0; bits_shift = 3'b100;
			#12 dir = 0; bits_shift = 3'b101;
			#12 dir = 0; bits_shift = 3'b110;
			#12 dir = 0; bits_shift = 3'b111;
			#12 dir=1; bits_shift=3'b000;
		end
	initial
		begin
			$dumpfile("test.vcd");
			$dumpvars(0,test);
		end
	
endmodule

Barrel_Shifter/test.vcd
$date
	Wed Sep 14 12:05:19 2022
$end
$version
	Icarus Verilog
$end
$timescale
	1s
$end
$scope module test $end
$var wire 8 ! Data [7:0] $end
$var wire 8 " bits_data [7:0] $end
$var reg 3 # bits_shift [2:0] $end
$var reg 1 $ dir $end
$scope module bs $end
$var wire 8 % Data [7:0] $end
$var wire 3 & bits_shift [2:0] $end
$var wire 1 $ dir $end
$var reg 8 ' bits_data [7:0] $end
$upscope $end
$upscope $end
$enddefinitions $end
#0
$dumpvars
b10001110 '
b0 &
b10001110 %
1$
b0 #
b10001110 "
b10001110 !
$end
#12
b11101 "
b11101 '
b1 #
b1 &
#24
b111010 "
b111010 '
b10 #
b10 &
#36
b1110100 "
b1110100 '
b11 #
b11 &
#48
b11101000 "
b11101000 '
b100 #
b100 &
#60
b11010001 "
b11010001 '
b101 #
b101 &
#72
b10100011 "
b10100011 '
b110 #
b110 &
#84
b1000111 "
b1000111 '
b111 #
b111 &
#96
b10001110 "
b10001110 '
b0 #
b0 &
0$
#108
b1000111 "
b1000111 '
b1 #
b1 &
#120
b10100011 "
b10100011 '
b10 #
b10 &
#132
b11010001 "
b11010001 '
b11 #
b11 &
#144
b11101000 "
b11101000 '
b100 #
b100 &
#156
b1110100 "
b1110100 '
b101 #
b101 &
#168
b111010 "
b111010 '
b110 #
b110 &
#180
b11101 "
b11101 '
b111 #
b111 &
#192
b10001110 "
b10001110 '
b0 #
b0 &
1$
